spaceone/__init__.py
spaceone/notification/__init__.py
spaceone/notification/conf/__init__.py
spaceone/notification/conf/global_conf.py
spaceone/notification/conf/proto_conf.py
spaceone/notification/conf/protocol_conf.py
spaceone/notification/connector/__init__.py
spaceone/notification/connector/identity_connector.py
spaceone/notification/connector/notification_plugin_connector.py
spaceone/notification/connector/plugin_connector.py
spaceone/notification/connector/repository_connector.py
spaceone/notification/connector/secret_connector.py
spaceone/notification/error/__init__.py
spaceone/notification/error/channel.py
spaceone/notification/error/jsonschema.py
spaceone/notification/error/plugin.py
spaceone/notification/error/protocol.py
spaceone/notification/error/quota.py
spaceone/notification/info/__init__.py
spaceone/notification/info/common_info.py
spaceone/notification/info/notification_info.py
spaceone/notification/info/notification_usage_info.py
spaceone/notification/info/project_channel_info.py
spaceone/notification/info/protocol_info.py
spaceone/notification/info/quota_info.py
spaceone/notification/info/user_channel_info.py
spaceone/notification/interface/__init__.py
spaceone/notification/interface/grpc/__init__.py
spaceone/notification/interface/grpc/v1/__init__.py
spaceone/notification/interface/grpc/v1/notification.py
spaceone/notification/interface/grpc/v1/notification_usage.py
spaceone/notification/interface/grpc/v1/project_channel.py
spaceone/notification/interface/grpc/v1/protocol.py
spaceone/notification/interface/grpc/v1/quota.py
spaceone/notification/interface/grpc/v1/user_channel.py
spaceone/notification/interface/task/__init__.py
spaceone/notification/interface/task/v1/__init__.py
spaceone/notification/interface/task/v1/delete_old_notification_scheduler.py
spaceone/notification/lib/__init__.py
spaceone/notification/lib/schedule.py
spaceone/notification/lib/schema.py
spaceone/notification/manager/__init__.py
spaceone_notification-1.12.0.dist-info/METADATA
spaceone_notification-1.12.0.dist-info/WHEEL
spaceone_notification-1.12.0.dist-info/top_level.txt
spaceone_notification-1.12.0.dist-info/RECORD
